{
	"_id": "tesQXaTdi9T8RxJU",
	"_key": "!macros!tesQXaTdi9T8RxJU",
	"author": "OKzfXIxFsK2wBLYU",
	"command": "/**\n ***************************************************************\n * This macro can be used to roll d20 Skill Tests.\n **************************************************************/\n\nfallout.Dialog2d20.createDialog({\n\tattribute: 1,\n\tcomplication: 20,\n\tdiceNum: 2,\n\tskill: 1,\n\ttag: false,\n});",
	"folder": null,
	"img": "systems/fallout/assets/icons/macro/d20-roller.svg",
	"name": "D20 Roller",
	"scope": "global",
	"type": "script"
}
