{
	"_id": "ZgOppC2XynIyM1bg",
	"_key": "!items!ZgOppC2XynIyM1bg",
	"effects": [
	],
	"folder": null,
	"img": "systems/fallout/assets/icons/items/robot_mod.svg",
	"name": "Hazard Detection Mod",
	"system": {
		"cost": 25,
		"description": "<p>Developed for cheap, disposable trap-clearance robots to accompany soldiers in enemy territory, this hazard detection and analysis system modifies the robot&rsquo;s sensory awareness to identify and categorize potential environmental threats and hazards. Repurposed for the Miss Nanny to spot dangers to children in the household, the system&rsquo;s developers never fully removed the urge to go towards hazards to investigate them more closely.</p>",
		"effect": "<p>Reduce the difficulty of Survival tests to detect and disable traps and similar hazards by 1 (min. 0)</p>",
		"equippable": true,
		"equipped": false,
		"favorite": false,
		"perks": "",
		"quantity": 1,
		"rarity": 2,
		"source": "",
		"stashed": false,
		"weight": 0
	},
	"type": "robot_mod"
}
