{
	"_id": "gD1wycvvp1ivtXdY",
	"_key": "!items!gD1wycvvp1ivtXdY",
	"effects": [
	],
	"folder": "IoEvCm1c8TK0ekL7",
	"img": "systems/fallout/assets/icons/items/perk.svg",
	"name": "Duck and Cover!",
	"system": {
		"description": "<p>Once, when you are affected by a Blast weapon, you may choose to fall prone (p.25). If you do so, you add +3 to all damage resistances against the damage caused by that Blast. If you later learn this perk, you may use whenever you are affected by a Blast weapon by spending 1 AP.</p>",
		"favorite": false,
		"rank": {
			"max": 1,
			"value": 0
		},
		"requirements": "",
		"requirementsEx": {
			"attributes": {
				"agi": {
					"value": 0
				},
				"cha": {
					"value": 0
				},
				"end": {
					"value": 0
				},
				"int": {
					"value": 0
				},
				"luc": {
					"value": 0
				},
				"per": {
					"value": 0
				},
				"str": {
					"value": 0
				}
			},
			"isCompanion": false,
			"level": 1,
			"levelIncrease": 0,
			"magazineUuids": [
				"Compendium.fallout.books_and_magz.Item.ZTVTUHilc84UzoRP"
			],
			"notGhoul": false,
			"notHuman": false,
			"notRadiationImmune": false,
			"notRobot": false,
			"notSupermutant": false
		},
		"source": "core_rulebook"
	},
	"type": "perk"
}
