{
	"_id": "RkftnkHGKVnz6URN",
	"_key": "!items!RkftnkHGKVnz6URN",
	"effects": [
	],
	"folder": null,
	"img": "systems/fallout/assets/icons/items/perk.svg",
	"name": "Rifleman",
	"system": {
		"description": "<p>When you make a ranged attack with any two-handed weapon with a Fire Rate of 2 or lower (except heavy weapons), you add +1 CD to the weapon&rsquo;s damage per rank.</p>\n<p>At rank 2, you also add the Piercing 1 damage effect, or add +1 to the rating of any Piercing X damage effect the weapon already had. Each time you take this perk, the level requirement increases by 4.</p>",
		"favorite": false,
		"rank": {
			"levelIncrease": 0,
			"levelStart": 1,
			"max": 2,
			"value": 0
		},
		"requirements": "AGI 7, Level 2+",
		"source": ""
	},
	"type": "perk"
}
