{
	"_id": "EoYPJPrpfi9ZRDy5",
	"_key": "!items!EoYPJPrpfi9ZRDy5",
	"effects": [
	],
	"folder": "OvlGhKtZemOqxcAN",
	"img": "systems/fallout/assets/icons/items/apparel_mod.svg",
	"name": "T-60c Helm",
	"system": {
		"apparelType": "powerArmor",
		"attachable": true,
		"attached": false,
		"canBeScrapped": true,
		"cost": 64,
		"description": "",
		"effect": "",
		"favorite": false,
		"health": {
			"value": 2
		},
		"isJunk": false,
		"location": "Head",
		"modType": "upgrade",
		"perks": "3",
		"quantity": 1,
		"rarity": "common",
		"resistance": {
			"energy": 1,
			"physical": 1,
			"radiation": 0
		},
		"shadowed": false,
		"source": "core_rulebook",
		"stashed": false,
		"summary": "",
		"weight": 3
	},
	"type": "apparel_mod"
}
